Metadata-Version: 2.1
Name: ludicrousdns
Version: 0.4.0
Summary: A ludicrously speedy DNS resolver
Home-page: https://gitlab.com/sheddow/ludicrousdns
Author: Sigurd Kolltveit
Author-email: sigurd.kolltveit@gmx.com
License: MIT
Platform: UNKNOWN
Classifier: Programming Language :: Python :: 3
Classifier: License :: OSI Approved :: MIT License
Classifier: Operating System :: OS Independent
Requires-Python: >=3.5
